mk_mpu6050_tools/Remote.py
mk_mpu6050_tools/Visulize.py
mk_mpu6050_tools/__init__.py
mk_mpu6050_tools-1.1.31.dist-info/LICENSE
mk_mpu6050_tools-1.1.31.dist-info/METADATA
mk_mpu6050_tools-1.1.31.dist-info/WHEEL
mk_mpu6050_tools-1.1.31.dist-info/top_level.txt
mk_mpu6050_tools-1.1.31.dist-info/RECORD
