Metadata-Version: 2.1
Name: mk-mpu6050-tools
Version: 1.1.31
Summary: Mk MPU6050 Tool Kit
Home-page: https://mknxgn.com/
Author: Mark Cartagena
Author-email: mark@mknxgn.com
License: UNKNOWN
Platform: UNKNOWN
Classifier: Programming Language :: Python :: 3
Classifier: License :: OSI Approved :: MIT License
Classifier: Operating System :: OS Independent
Requires-Dist: mknxgn-essentials
Requires-Dist: requests
